selectron/__about__.py
selectron/__init__.py
selectron/entry_points.py
selectron/lib.py
selectron/ai/codegen_agent.py
selectron/ai/codegen_prompt.py
selectron/ai/codegen_utils.py
selectron/ai/propose_selection.py
selectron/ai/selector_agent.py
selectron/ai/selector_prompt.py
selectron/ai/selector_tools.py
selectron/ai/types.py
selectron/chrome/cdp_executor.py
selectron/chrome/chrome_cdp.py
selectron/chrome/chrome_highlighter.py
selectron/chrome/chrome_launcher.py
selectron/chrome/chrome_monitor.py
selectron/chrome/chrome_tab_manager.py
selectron/chrome/connect.py
selectron/chrome/diff_tabs.py
selectron/chrome/tab_interaction_handler.py
selectron/chrome/types.py
selectron/cli/__init__.py
selectron/cli/app.py
selectron/cli/app_state.py
selectron/cli/duckdb_utils.py
selectron/cli/home_panel.py
selectron/cli/log_panel.py
selectron/cli/monitor_handler.py
selectron/cli/settings_panel.py
selectron/cli/styles.tcss
selectron/dom/buildDomTree.js
selectron/dom/dom_attributes.py
selectron/dom/dom_service.py
selectron/dom/dom_views.py
selectron/dom/enhanced_css_selector.py
selectron/dom/history_tree_processor.py
selectron/dom/history_tree_views.py
selectron/parse/execution.py
selectron/parse/parser_fallback.py
selectron/parse/parser_registry.py
selectron/parse/types.py
selectron/parsers/linkedin.com~~2ffeed.json
selectron/parsers/news.ycombinator.com.json
selectron/parsers/x.com~~2f0thernet~~2fverified_followers.json
selectron/parsers/x.com~~2fhome.json
selectron/util/__init__.py
selectron/util/debug_helpers.py
selectron/util/get_app_dir.py
selectron/util/image_utils.py
selectron/util/logger.py
selectron/util/model_config.py
selectron/util/open_log_file.py
selectron/util/resolve_urls.py
selectron/util/sample_items.py
selectron/util/slugify_url.py
selectron/util/time_execution.py
selectron-0.0.1.dist-info/METADATA
selectron-0.0.1.dist-info/WHEEL
selectron-0.0.1.dist-info/entry_points.txt
selectron-0.0.1.dist-info/licenses/LICENSE
selectron-0.0.1.dist-info/RECORD
